cpanbaidu/Auth.py
cpanbaidu/Downfile.py
cpanbaidu/File.py
cpanbaidu/Upload.py
cpanbaidu/User.py
cpanbaidu/__init__.py
cpanbaidu/authtype/OAuth.py
cpanbaidu/authtype/__init__.py
cpanbaidu/model/Base.py
cpanbaidu/model/FileModel.py
cpanbaidu/model/UserModel.py
cpanbaidu/model/model.py
cpanbaidu/utils/Constants.py
cpanbaidu/utils/EnvConfig.py
cpanbaidu/utils/Logger.py
cpanbaidu/utils/__init__.py
cpanbaidu/utils/download.py
cpanbaidu/utils/md5.py
cpanbaidu/utils/sha.py
cpanbaidu-0.1.0.dist-info/WHEEL
cpanbaidu-0.1.0.dist-info/entry_points.txt
cpanbaidu-0.1.0.dist-info/METADATA
cpanbaidu-0.1.0.dist-info/RECORD
