Metadata-Version: 2.3
Name: cpanbaidu
Version: 0.1.0
Summary: 百度云盘的python接口文档(非官方)
Author: zoushucai
Author-email: zoushucai <zoushucai@users.noreply.github.com>
Requires-Dist: click>=8.3.0
Requires-Dist: dotenv>=0.9.9
Requires-Dist: httpx[http2]>=0.28.1
Requires-Dist: loguru>=0.7.3
Requires-Dist: py3-wget>=1.0.13
Requires-Dist: pydantic>=2.12.4
Requires-Dist: tenacity>=9.1.2
Requires-Dist: tqdm>=4.67.1
Requires-Python: >=3.10
Project-URL: Changelog, https://github.com/zoushucai/cpanbaidu/blob/main/CHANGELOG.md
Project-URL: Documentation, https://cpanbaidu.readthedocs.org
Project-URL: Homepage, https://github.com/zoushucai/cpanbaidu
Project-URL: Issues, https://github.com/zoushucai/cpanbaidu/issues
Project-URL: Repository, https://github.com/zoushucai/cpanbaidu.git
